agents/__init__.py
agents/base_agent.py
agents/critic.py
agents/editor.py
agents/researcher.py
agents/storyteller.py
sollol_backup_20251005/__init__.py
sollol_backup_20251005/adapters.py
sollol_backup_20251005/adaptive_metrics.py
sollol_backup_20251005/aggregation.py
sollol_backup_20251005/auth.py
sollol_backup_20251005/autobatch.py
sollol_backup_20251005/batch.py
sollol_backup_20251005/cli.py
sollol_backup_20251005/client.py
sollol_backup_20251005/cluster.py
sollol_backup_20251005/config.py
sollol_backup_20251005/discovery.py
sollol_backup_20251005/execution.py
sollol_backup_20251005/gateway.py
sollol_backup_20251005/gpu_controller.py
sollol_backup_20251005/hedging.py
sollol_backup_20251005/hybrid_router.py
sollol_backup_20251005/intelligence.py
sollol_backup_20251005/llama_cpp_coordinator.py
sollol_backup_20251005/llama_cpp_rpc.py
sollol_backup_20251005/memory.py
sollol_backup_20251005/metrics.py
sollol_backup_20251005/ollama_gguf_resolver.py
sollol_backup_20251005/pool.py
sollol_backup_20251005/prioritization.py
sollol_backup_20251005/rpc_auto_setup.py
sollol_backup_20251005/rpc_discovery.py
sollol_backup_20251005/rpc_registry.py
sollol_backup_20251005/serve.py
sollol_backup_20251005/setup.py
sollol_backup_20251005/setup_llama_cpp.py
sollol_backup_20251005/sollol.py
sollol_backup_20251005/tasks.py
sollol_backup_20251005/workers.py
synaptic_llamas-0.1.0.dist-info/METADATA
synaptic_llamas-0.1.0.dist-info/WHEEL
synaptic_llamas-0.1.0.dist-info/entry_points.txt
synaptic_llamas-0.1.0.dist-info/top_level.txt
synaptic_llamas-0.1.0.dist-info/RECORD
