Metadata-Version: 2.4
Name: synaptic-llamas
Version: 0.1.0
Summary: Distributed Parallel AI Agent Orchestration with Intelligent Load Balancing
Home-page: https://github.com/BenevolentJoker-JohnL/SynapticLlamas
Author: BenevolentJoker-JohnL
Author-email: benevolentjoker@gmail.com
Project-URL: Bug Tracker, https://github.com/BenevolentJoker-JohnL/SynapticLlamas/issues
Project-URL: Documentation, https://github.com/BenevolentJoker-JohnL/SynapticLlamas/blob/main/README.md
Project-URL: Source Code, https://github.com/BenevolentJoker-JohnL/SynapticLlamas
Keywords: ai llm distributed orchestration load-balancing ollama agents
Classifier: Development Status :: 3 - Alpha
Classifier: Intended Audience :: Developers
Classifier: Intended Audience :: Science/Research
Classifier: Topic :: Scientific/Engineering :: Artificial Intelligence
Classifier: Topic :: System :: Distributed Computing
Classifier: License :: OSI Approved :: MIT License
Classifier: Programming Language :: Python :: 3
Classifier: Programming Language :: Python :: 3.8
Classifier: Programming Language :: Python :: 3.9
Classifier: Programming Language :: Python :: 3.10
Classifier: Programming Language :: Python :: 3.11
Classifier: Operating System :: OS Independent
Requires-Python: >=3.8
Requires-Dist: requests>=2.31.0
Requires-Dist: httpx>=0.24.0
Requires-Dist: ipaddress>=1.0.23
Requires-Dist: dask[distributed]>=2024.1.0
Requires-Dist: rich>=13.7.0
Requires-Dist: flask
Requires-Dist: flask-cors
Requires-Dist: flask-sock
Requires-Dist: waitress>=3.0.0
Requires-Dist: asyncio>=3.4.3
Requires-Dist: sollol>=0.9.10
Provides-Extra: dev
Requires-Dist: pytest>=7.4.0; extra == "dev"
Requires-Dist: pytest-cov>=4.1.0; extra == "dev"
Requires-Dist: pytest-mock>=3.11.1; extra == "dev"
Requires-Dist: pytest-xdist>=3.3.1; extra == "dev"
Requires-Dist: black>=23.7.0; extra == "dev"
Requires-Dist: isort>=5.12.0; extra == "dev"
Requires-Dist: flake8>=6.1.0; extra == "dev"
Requires-Dist: mypy>=1.5.0; extra == "dev"
Requires-Dist: pylint>=2.17.5; extra == "dev"
Requires-Dist: pre-commit>=3.3.3; extra == "dev"
Requires-Dist: coverage>=7.3.0; extra == "dev"
Dynamic: author
Dynamic: author-email
Dynamic: classifier
Dynamic: description
Dynamic: description-content-type
Dynamic: home-page
Dynamic: keywords
Dynamic: project-url
Dynamic: provides-extra
Dynamic: requires-dist
Dynamic: requires-python
Dynamic: summary
